README
setup.py
ct_schools/__init__.py
ct_schools/helpers.py
ct_schools/schools.py
ct_schools.egg-info/PKG-INFO
ct_schools.egg-info/SOURCES.txt
ct_schools.egg-info/dependency_links.txt
ct_schools.egg-info/requires.txt
ct_schools.egg-info/top_level.txt
ct_schools/data/schools.csv