Metadata-Version: 1.0
Name: ct-schools
Version: 0.0.6
Summary: Get data about Connecticut schools
Home-page: https://github.com/jakekara/ct_schools
Author: Jake Kara
Author-email: jake@jakekara.com
License: GPL-3
Platform: UNKNOWN
